routelookup/__init__.py
routelookup/addrmodule/__init__.py
routelookup/addrmodule/ipaddress/__init__.py
routelookup/addrmodule/netaddr/__init__.py
routelookup/api.py
routelookup/compat.py
routelookup/ipmath.py
routelookup/py.typed
routelookup/python_ipaddress/LICENSE
routelookup/python_ipaddress/__init__.py
routelookup/pytricia/__init__.py
routelookup/routetable/__init__.py
routelookup/typehints.py
routelookup-1.0.3.dist-info/LICENSE
routelookup-1.0.3.dist-info/METADATA
routelookup-1.0.3.dist-info/WHEEL
routelookup-1.0.3.dist-info/RECORD
