Metadata-Version: 2.1
Name: routelookup
Version: 1.0.3
Summary: Routing table-style IP prefix lookups
License: MIT
Keywords: cidr,ip,lookup,prefix,route,routing table
Author: carter1643
Author-email: carter1643@pm.me
Requires-Python: >=3.10,<4.0
Classifier: Development Status :: 4 - Beta
Classifier: Intended Audience :: Developers
Classifier: Intended Audience :: Telecommunications Industry
Classifier: License :: OSI Approved :: MIT License
Classifier: Programming Language :: Python :: 3
Classifier: Programming Language :: Python :: 3.10
Classifier: Programming Language :: Python :: 3.11
Classifier: Programming Language :: Python :: 3.12
Classifier: Programming Language :: Python :: 3.13
Classifier: Topic :: System :: Networking
Project-URL: repository, https://github.com/carter1643/routelookup
